{
    "operations": {
        "markdown.raw": {
            "httpMethod": "POST",
            "uri": "/markdown/raw",
            "parameters": {
                "text": {
                    "location": "body",
                    "required": true
                },
                "content-type": {
                    "location": "header",
                    "required": true,
                    "default": "text/x-markdown"
                }
            }
        },
        "repos.blobs.get": {
            "httpMethod": "GET",
            "uri": "/repos/{owner}/{repo}/git/blobs/{sha}",
            "parameters": {
                "owner": {
                    "location": "uri",
                    "required": true
                },
                "repo": {
                    "location": "uri",
                    "required": true
                },
                "sha": {
                    "location": "uri",
                    "required": true
                }
            }
        },
        "repos.branch.get": {
            "httpMethod": "GET",
            "uri": "/repos/{owner}/{repo}/branches/{branch}",
            "parameters": {
                "owner": {
                    "location": "uri",
                    "required": true
                },
                "repo": {
                    "location": "uri",
                    "required": true
                },
                "branch": {
                    "location": "uri",
                    "required": true
                }
            }
        },
        "repos.commits.compare": {
            "httpMethod": "GET",
            "uri": "/repos/{owner}/{repo}/compare/{base}...{head}",
            "parameters": {
                "owner": {
                    "location": "uri",
                    "required": true
                },
                "repo": {
                    "location": "uri",
                    "required": true
                },
                "base": {
                    "location": "uri",
                    "required": true
                },
                "head": {
                    "location": "uri",
                    "required": true
                }
            }
        },
        "repos.commits.get": {
            "httpMethod": "GET",
            "uri": "/repos/{owner}/{repo}/commits/{sha}",
            "parameters": {
                "owner": {
                    "location": "uri",
                    "required": true
                },
                "repo": {
                    "location": "uri",
                    "required": true
                },
                "sha": {
                    "location": "uri",
                    "required": true
                }
            }
        },
        "repos.content.get": {
            "httpMethod": "GET",
            "uri": "/repos/{owner}/{repo}/contents/{path}",
            "parameters": {
                "owner": {
                    "location": "uri",
                    "required": true
                },
                "repo": {
                    "location": "uri",
                    "required": true
                },
                "path": {
                    "location": "uri",
                    "required": true
                }
            }
        },
        "repos.get": {
            "httpMethod": "GET",
            "uri": "/repos/{owner}/{repo}",
            "parameters": {
                "owner": {
                    "location": "uri",
                    "required": true
                },
                "repo": {
                    "location": "uri",
                    "required": true
                }
            }
        },
        "repos.trees.get": {
            "httpMethod": "GET",
            "uri": "/repos/{owner}/{repo}/git/trees/{sha}",
            "parameters": {
                "owner": {
                    "location": "uri",
                    "required": true
                },
                "repo": {
                    "location": "uri",
                    "required": true
                },
                "sha": {
                    "location": "uri",
                    "required": true
                },
                "recursive": {
                    "location": "query",
                    "required": false,
                    "type": "integer"
                }
            }
        }
    }
}
